README.md
setup.cfg
setup.py
prometheus_aws_configservice_exporter/__init__.py
prometheus_aws_configservice_exporter/cli.py
prometheus_aws_configservice_exporter/collector.py
prometheus_aws_configservice_exporter.egg-info/PKG-INFO
prometheus_aws_configservice_exporter.egg-info/SOURCES.txt
prometheus_aws_configservice_exporter.egg-info/dependency_links.txt
prometheus_aws_configservice_exporter.egg-info/entry_points.txt
prometheus_aws_configservice_exporter.egg-info/requires.txt
prometheus_aws_configservice_exporter.egg-info/top_level.txt