Metadata-Version: 2.1
Name: prometheus-aws-configservice-exporter
Version: 1.0.6
Summary: Prometheus exporter for AWS Config
Home-page: https://github.com/AirWalk-Digital/prometheus-aws-configservice-exporter
Author: Jim Lamb
Author-email: jim.lamb@airwalkconsulting.com
License: UNKNOWN
Download-URL: https://github.com/AirWalk-Digital/prometheus-aws-configservice-exporter/archive/1.0.6.tar.gz
Keywords: prometheus,aws,config,configservice
Platform: UNKNOWN
Requires-Python:  >= 3
Provides-Extra: dev
